<?xml version="1.0" encoding="UTF-8"?>
<!DOCTYPE document PUBLIC "-//APACHE//DTD Documentation V2.0//EN"
"http://forrest.apache.org/dtd/document-v20.dtd">
<document>
    <header>
        <title>Velkommen til våre læringsprogram</title>
    </header>

    <body>
<p><a href="index.html">Davvisámegillii</a> | <a href="index.eng.html">In English</a> | <a href="index.rus.html">По-русский</a> </p>
		<p></p>
    <p><img alt="sahkaicon img" width="150" class="align-right" src="images/sahkaicon.png" /></p>
		<p></p>
        <p>Læringsprogram:</p> 
         <ul>
        <li><a href="OAHPAveiledning.nno.html"><em>OAHPA-davvi</em></a> for å lære nordsamisk</li> 
       <li><a href="sma/index.html"><em>OAHPA-åarjel</em></a> for å lære sørsamisk</li>
       <li><a href="sma/index.html"><em>OAHPA-kildin</em></a> for å lære kildinsamisk</li>
        </ul>
        <p>Grammatikkprogram:</p> 
         <ul>
        <li><a href="VISL_spealut.nno.html"><em>VISL</em></a> for å lære nordsamisk grammatikk for 1. språkselever</li> 
        </ul>
		<p></p>
		<p></p>
       
 		<p></p>
    </body>
</document>
