<?xml version="1.0" encoding="UTF-8"?>

<site label="OAHPA!" href="" xmlns="http://apache.org/forrest/linkmap/1.0" tab="">
  <about label="OAHPA!-portála:">
    <index label=" " href="index.html" description="Bures boahtin OAHPA!-portálii"/>

  <L2 label="Giellaoahppan-fálaldagat:">
    <quiz label="Quiz" href="quiz.html"/>
    <sojahanharjehusat  label="Sojahallanhárjehusat" href="sojahanharjehusat.html"/>
    <jearratvastidit  label="(Jearrat/vástidit)" href="jearratvastidit.html"/>
    <sagastallamat  label="(Ságastallamat)" href="sagastallamat.html"/>       
    <satnevuorka  label="(OAHPA! sátnevuorká)" href="satnevuorka.html"/>  
  </L2>
  <L1 label="Grammatihkka-oahppanfálaldagat:">
    <satneluohkkaspealut label="Sátneluohkkáspealut" href="satneluohkkaspealut.html"/>
    <cealkkacoavdinspealut label="Cealkkačoavdin-spealut" href="cealkkacoavdinspealut.html"/>
    <cealkkacoavdinmuorra label="Cealkkamuorra" href="cealkkacoavdinmuorra.html"/>
  </L1>
  <res label="Oahppan-resurssat:">
    <paradigmat  label="Grammatihkka ja paradigmat" href="paradigmat.html"/>
    <satnegirji  label="Sátnegirji ja lohkosánit" href="satnegirji.html"/>
    <analyseren  label="Sátne- ja teakstanalyseren" href="analyseren.html"/>
  </res>
  </about>  
<norwegian label="Læringsportal:" tab="norsk">
  <about label="Velkomen">
    <index label="Intro" href="norsk.html" description="Velkomen til læringsportalen"/>
  </about>
  <L2 label="Språklærings-tilbud:">
    <quiz label="Quiz" href="quiz.nno.html"/>
    <sojahanharjehusat  label="Bøyingsøvingar" href="sojahanharjehusat.nno.html"/>
    <jearratvastidit  label="(Spørre/svare)" href="jearratvastidit.nno.html"/>
    <sagastallamat  label="(Dialogar)" href="sagastallamat.nno.html"/>
    <satnevuorka  label="(OAHPA! ordtilfang)" href="satnevuorka.nno.html"/>
  </L2>
  <L1 label="Grammatikk-læringstilbud:">    
   <satneluohkkaspealut label="Ordklassespel" href="satneluohkkaspealut.nno.html"/>
    <cealkkacoavdinspealut label="Setningsanalyse-spel" href="cealkkacoavdinspealut.nno.html"/>
    <cealkkacoavdinmuorra label="Setningstre" href="cealkkacoavdinmuorra.nno.html"/>
  </L1>
  <res label="Læringsressursar:">
    <paradigmat  label="Grammatikk og paradigme" href="paradigmat.nno.html"/>
    <satnegirji  label="Ordbok og talord" href="satnegirji.nno.html"/>
    <analyseren  label="Ord- og tekstanalyse" href="analyseren.nno.html"/> 
  </res>
  </norwegian>
<!--  Sub menus    -->
<!--  <english label="In English" tab="english">
  <about label="Learning portal:">
    <index label=" " href="english.html" description="Welcome to the Sámi learning portal"/>
    <satneluohkkaspealut label="Part of speech game" href="satneluohkkaspealut.eng.html"/>
    <cealkkacoavdinspealut label="Sentence analysis" href="cealkkacoavdinspealut.eng.html"/>
    <cealkkacoavdinmuorra label="Sentence tree" href="cealkkacoavdinmuorra.eng.html"/>
    <quiz label="Quiz" href="quiz.eng.html"/>
    <sojahanharjehusat  label="Paradigm exersises" href="sojahanharjehusat.eng.html"/>
    <jearratvastidit  label="Questions/answers" href="jearratvastidit.eng.html"/>
    <sagastallamat  label="Dialogues" href="sagastallamat.eng.html"/>
    <paradigmat  label="Grammars and paradigms" href="paradigmat.eng.html"/>
    <satnevuorka  label="OAHPA! vocabulary" href="satnevuorka.eng.html"/>
    <satnegirji  label="Dictionary and numerals" href="satnegirji.eng.html"/>
    <analyseren  label="Word and text analysis" href="analyseren.eng.html"/>
  </about>
  </english>-->

  
</site>
