<?xml version="1.0" encoding="UTF-8"?>
<r xml:lang="fkv">
   <e>
      <lg>
         <l pos="Pron" stem="xxx">mik채</l>
      </lg>
      <dialect class=""/>
      <sources/>
      <mg>
         <semantics>
            <sem class="CLADV"/>
         </semantics>
         <tg xml:lang="fkv">
            <t stat="pref"/>
         </tg>
         <tg xml:lang="nob"/>
         <tg xml:lang="fin"/>
         <tg xml:lang="eng"/>
      </mg>
   </e>
   <e>
      <lg>
         <l pos="Adv" stem="xxx">t채n채채n</l>
      </lg>
      <dialect class=""/>
      <sources/>
      <mg>
         <semantics>
            <sem class="CLADV"/>
         </semantics>
         <tg xml:lang="fkv">
            <t stat="pref"/>
         </tg>
         <tg xml:lang="nob"/>
         <tg xml:lang="fin"/>
         <tg xml:lang="eng"/>
      </mg>
   </e>
   <e>
      <lg>
         <l pos="Adv" stem="xxx">eilen</l>
      </lg>
      <dialect class=""/>
      <sources/>
      <mg>
         <semantics>
            <sem class="CLADV"/>
         </semantics>
         <tg xml:lang="fkv">
            <t stat="pref"/>
         </tg>
         <tg xml:lang="nob"/>
         <tg xml:lang="fin"/>
         <tg xml:lang="eng"/>
      </mg>
   </e>
</r>