<questions>
  <q id="vtiprs1">
    <qtype>V-TI-PRS</qtype>
    <question>
      <text>MAINVOBJ cî mâna OBJECT</text>
      <element id="MAINVOBJ">
            <grammar tag="V+TI+Ind+Prs+2Sg"/>
        <sem class="mACTIVITY"/>
      </element>
      <element id="OBJECT">
            <grammar tag="N+AN+Sg"/>
			<sem class="mOBJECT"/>
      </element>
    </question>
    <answer> 
      <text>êha, MAINVOBJ mâna OBJECT</text>
      <element game='morfa' id="MAINVOBJ" content="MAINVOBJ" task="yes">
        <grammar tag="V+TI+Ind+Prs+1Sg"/>
      </element>
      <element id="OBJECT">
        <grammar tag="N+AN+Sg"/>
      </element>
    </answer>
    <answer> 
      <text>namôya, namôya MAINVOBJ mâna OBJECT</text>
      <element game='morfa' id="MAINVOBJ" content="MAINVOBJ" task="yes">
        <grammar tag="V+TI+Ind+Prs+1Sg"/>
      </element>
      <element id="OBJECT">
        <grammar tag="N+AN+Sg"/>
      </element>
    </answer>
  </q>
  <q id="vtiprs2">
    <qtype>V-TI-PRS</qtype>
    <question>
      <text>MAINVOBJ cî mâna OBJECT</text>
      <element id="MAINVOBJ">
            <grammar tag="V+TI+Ind+Prs+3Sg"/>
        <sem class="mACTIVITY"/>
      </element>
      <element id="OBJECT">
            <grammar tag="N+AN+Sg"/>
      <sem class="mOBJECT"/>
      </element>
    </question>
    <answer> 
      <text>êha, MAINVOBJ mâna OBJECT</text>
      <element game='morfa' id="MAINVOBJ" content="MAINVOBJ" task="yes">
        <grammar tag="V+TI+Ind+Prs+3Sg"/>
      </element>
      <element id="OBJECT">
        <grammar tag="N+AN+Sg"/>
      </element>
    </answer>
    <answer> 
      <text>namôya, namôya MAINVOBJ mâna OBJECT</text>
      <element game='morfa' id="MAINVOBJ" content="MAINVOBJ" task="yes">
        <grammar tag="V+TI+Ind+Prs+3Sg"/>
      </element>
      <element id="OBJECT">
        <grammar tag="N+AN+Sg"/>
      </element>
    </answer>
  </q>
  <q id="vtiprs3">
    <qtype>V-TI-PRS</qtype>
    <question>
      <text>MAINVOBJ cî mâna OBJECT</text>
      <element id="MAINVOBJ">
            <grammar tag="V+TI+Ind+Prs+2Pl"/>
        <sem class="mACTIVITY"/>
      </element>
      <element id="OBJECT">
            <grammar tag="N+AN+Sg"/>
			<sem class="mOBJECT"/>
      </element>
    </question>
    <answer> 
      <text>êha, MAINVOBJ mâna OBJECT</text>
      <element game='morfa' id="MAINVOBJ" content="MAINVOBJ" task="yes">
        <grammar tag="V+TI+Ind+Prs+1Pl"/>
      </element>
      <element id="OBJECT">
        <grammar tag="N+AN+Sg"/>
      </element>
    </answer>
    <answer> 
      <text>namôya, namôya MAINVOBJ mâna OBJECT</text>
      <element game='morfa' id="MAINVOBJ" content="MAINVOBJ" task="yes">
        <grammar tag="V+TI+Ind+Prs+1Pl"/>
      </element>
      <element id="OBJECT">
        <grammar tag="N+AN+Sg"/>
      </element>
    </answer>
  </q>
  <q id="vtiprs4">
    <qtype>V-TI-PRS</qtype>
    <question>
      <text>MAINVOBJ cî mâna OBJECT</text>
      <element id="MAINVOBJ">
        <grammar tag="V+TI+Ind+Prs+3Sg"/>
        <sem class="TASTE"/>
		<sem class="PREPARE_FOOD"/>
      </element>
      <element id="OBJECT">
            <grammar tag="N+AN+Sg"/>
			<sem class="FOOD"/>
      </element>
    </question>
    <answer> 
      <text>êha, MAINVOBJ mâna OBJECT</text>
      <element game='morfa' id="MAINVOBJ" content="MAINVOBJ" task="yes">
        <grammar tag="V+TI+Ind+Prs+3Sg"/>
      </element>
      <element id="OBJECT">
        <grammar tag="N+AN+Sg"/>
      </element>
    </answer>
    <answer> 
      <text>namôya, namôya MAINVOBJ mâna OBJECT</text>
      <element game='morfa' id="MAINVOBJ" content="MAINVOBJ" task="yes">
        <grammar tag="V+TI+Ind+Prs+3Sg"/>
      </element>
      <element id="OBJECT">
        <grammar tag="N+AN+Sg"/>
      </element>
    </answer>
  </q>
  <q id="vtiprs5">
    <qtype>V-TI-PRS</qtype>
    <question>
      <text>MAINVOBJ cî mâna OBJECT</text>
      <element id="MAINVOBJ">
            <grammar tag="V+TI+Ind+Prs+12Pl"/>
        <sem class="mACTIVITY"/>
      </element>
      <element id="OBJECT">
            <grammar tag="N+AN+Sg"/>
			<sem class="mOBJECT"/>
      </element>
    </question>
    <answer> 
      <text>êha, MAINVOBJ mâna OBJECT</text>
      <element game='morfa' id="MAINVOBJ" content="MAINVOBJ" task="yes">
        <grammar tag="V+TI+Ind+Prs+12Pl"/>
      </element>
      <element id="OBJECT">
        <grammar tag="N+AN+Sg"/>
      </element>
    </answer>
    <answer> 
      <text>namôya, namôya MAINVOBJ mâna OBJECT</text>
      <element game='morfa' id="MAINVOBJ" content="MAINVOBJ" task="yes">
        <grammar tag="V+TI+Ind+Prs+12Pl"/>
      </element>
      <element id="OBJECT">
        <grammar tag="N+AN+Sg"/>
      </element>
    </answer>
  </q>
  <q id="vtiprs6">
    <qtype>V-TI-PRS</qtype>
    <question>
      <text>MAINVOBJ cî mâna OBJECT</text>
      <element id="MAINVOBJ">
            <grammar tag="V+TI+Ind+Prs+3Pl"/>
        <sem class="mACTIVITY"/>
      </element>
      <element id="OBJECT">
            <grammar tag="N+AN+Sg"/>
			<sem class="mOBJECT"/>
      </element>
    </question>
    <answer> 
      <text>êha, MAINVOBJ mâna OBJECT</text>
      <element game='morfa' id="MAINVOBJ" content="MAINVOBJ" task="yes">
        <grammar tag="V+TI+Ind+Prs+3Pl"/>
      </element>
      <element id="OBJECT">
        <grammar tag="N+AN+Sg"/>
      </element>
    </answer>
    <answer> 
      <text>namôya, namôya MAINVOBJ mâna OBJECT</text>
      <element game='morfa' id="MAINVOBJ" content="MAINVOBJ" task="yes">
        <grammar tag="V+TI+Ind+Prs+3Pl"/>
      </element>
      <element id="OBJECT">
        <grammar tag="N+AN+Sg"/>
      </element>
    </answer>
  </q>
  <q id="vtiprs7">
    <qtype>V-TI-PRS</qtype>
    <question>
      <text>MAINVOBJ cî mâna OBJECT</text>
      <element id="MAINVOBJ">
            <grammar tag="V+TI+Ind+Prs+4Sg/Pl"/>
        <sem class="mACTIVITY"/>
      </element>
      <element id="OBJECT">
            <grammar tag="N+AN+Sg"/>
			<sem class="mOBJECT"/>
      </element>
    </question>
    <answer> 
      <text>êha, MAINVOBJ mâna OBJECT</text>
      <element game='morfa' id="MAINVOBJ" content="MAINVOBJ" task="yes">
        <grammar tag="V+TI+Ind+Prs+4Sg/Pl"/>
      </element>
      <element id="OBJECT">
        <grammar tag="N+AN+Sg"/>
      </element>
    </answer>
    <answer> 
      <text>namôya, namôya MAINVOBJ mâna OBJECT</text>
      <element game='morfa' id="MAINVOBJ" content="MAINVOBJ" task="yes">
        <grammar tag="V+TI+Ind+Prs+4Sg/Pl"/>
      </element>
      <element id="OBJECT">
        <grammar tag="N+AN+Sg"/>
      </element>
    </answer>
  </q>
</questions>
