<?xml version="1.0" encoding="utf-8"?>


  <messages xml:lang="fin">
    <message id="err-no_fst">Valitettavasti ohjelma ei toimi juuri nyt.</message>
    <message id="err-nonword">WORDFORM ei löydy leksikostamme. Onkohan sanassa kirjoitusvirhe?</message>
    <message id="err-capProp">Sanassa WORDFORM pitää ehkä olla suuri alkukirjain?</message>
    <message id="err-Err">Sanassa WORDFORM on ehkä kirjoitusvirhe?</message>
    <message id="err-IllErr"><![CDATA[Voiko WORDFORM  ehkä olla väärin kirjoitettu <a href="/sme/gramm/substantiv.html#Illatiiva">illatiivi</a>?]]>?</message>
    <message id="err-longA">Sinä olet ehkä unohtanut kirjoittaa á sanassa WORDFORM</message>
    <message id="sem-dont-know">On liian yksinkertaista vastata en-tiedä. Yritä uudestaan.</message>
    <message id="grm-incorr-persnr-pron"><![CDATA[Onko <a class="helptext" target="_blank" href="#">pronomini<span class="shortinfo">Pronomini taivutetaan persoonassa, kuten suomessa, esim. mun, don, son, ja myös kaksikossa (moai, doai, soai) ja monikossa (mii, dii, sii).</span> WORDFORM taivutettu oikeassa persoonassa ja luvussa?]]></message>
    <message id="err-1pers-prfprc"><![CDATA[Tarkoitatko yksikön 1. persoona? WORDFORM-muodosta puuttuu <a class="helptext" target="_blank" href="/sme/gramm/stadieveksling.html#Dássemolsašuddanminstarat">astevaihtelu<span class="shortinfo">Konsonantit vaihtelevat kuten suomessakin, mutta saamessa melkein kaikki konsonantit osallistuvat, esim. -idn- > -inn-. Klikkaa lukeaksesi enemmän.</span>.]]>.</message>
    <message id="grm-should-be-Vfin"><![CDATA[Vastauksessasi pitäisi olla <a class="helptext" href="#">finiittinen verbi<span class="shortinfo">Finiittiverbi on taivutettu persoonassa ja ajassa, esim.: boran, lohká</span></a>. Olisiko kyseessä kirjoitusvirhe?]]></message>
    <message id="grm-soaitit">"soaitit"-verbiä pitää käyttää samalla tavalla kuin muut apuverbit, esim. Mun soaittán boahtit.</message>
    <message id="grm-should-not-Vfin">WORDFORM finiittinen - ehkä infinitiivi sopisi?<![CDATA[WORDFORM ei pitäisi olla <a class="helptext" href="#">finiittinen<span class="shortinfo">Finiittinen verbi taipuu personassa ja ajassa, kuten suomessakin, esim. boran, lohká</span></a>. <a class="helptext" href="#">Infinitiivi<span class="shortinfo">Verbin perusmuoto, esim: borrat, lohkat</span> sopii ehkä paremmin?]]></message>
    <message id="grm-not-verb-after-workverb">"bargat" ja "dahkat"-verbien jälkeen ei käytetä toista verbiä.</message>
    <message id="sem-answer-with-same-verb">Käytä tässä vastauksessa samaa verbiä kuin kysymyksessä.</message>
    <message id="sem-neg-verb"><![CDATA[Sinun pitää käyttää <a class="helptext" target="_blank" href="/sme/gramm/verb.html#Biehttaleapmi">kieltoverbiä.<span class="shortinfo">Saamen kieltoverbin muodat ovat in, it, ii jne. Klikkaa lukeaksesi enemmän.</span>.]]></message>
    <message id="sem-same-verb">Sinun pitää käyttää annettua verbiä.</message>
    <message id="sem-same-noun">Sinun pitää käyttää annettua substantiivia.</message>
    <message id="sem-same-adj">Sinun pitää käyttää annettua adjektiivia.</message>
    <message id="sem-same-pron">Sinun pitää käyttää annettua pronomenia.</message>
    <message id="sem-same-num">Sinun pitää käyttää annettua lukusanaa.</message>
    <message id="sem-same-po">Sinun pitää käyttää annettua postpositiota.</message>
    <message id="grm-Hab"><![CDATA[Muista käyttää <a class="helptext" target="_blank" href="/sme/gramm/syntaks.html#%27mus-lea%27-cealkagat+ja+eksistensiála+cealkagat">lokatiiviä<span class="shortinfo">Saamessa on sama omistusrakenne kuon suomessa, mutta omistaja on lokatiivissa. Omistettu on nominatiivissa: : Mánás lea spábba. Klikkaa lukeaksesi enemmän lokatiivista.</span></a>.]]></message>
    <message id="grm-should-Com"><![CDATA[WORDFORM pitää olla <a class="helptext" target="_blank" href="/sme/gramm/substantiv.html#Komitatiiva">komitatiivissa<span class="shortinfo">Suom komitatiivin lisäksi saamen komitatiivi vastaa myös suomen "lla": niibbiin, "veitsellä". Klikkaa lukeaksesi enemmän komitatiivista.</span></a> verbin jälkeen.]]></message>
    <message id="grm-should-Loc"><![CDATA[WORDFORM pitää olla <a class="helptext" target="_blank" href="/sme/gramm/substantiv.html#Lokatiiva">lokatiivissa<span class="shortinfo">Lokatiivi vastaa suomen allatiiviin, inessiivin, allatiiviin ja ablatiivin. Muodot ovat skuvllas, skuvllain. Klikkaa lukeaksesi enemmän lokatiivista.</span></a> verbin jälkeen.]]>.</message>
    <message id="err-VowIll"><![CDATA[Illatiivissa <a class="helptext" target="_blank" href="/sme/gramm/substantiv.html#Illatiiva">vokaalin pitää muuttua<span class="shortinfo">Sanan viimeinen vokaali muuttuu illatiivipäätteen takia: a > i, i > á, o > u. Klikkaa lukeaksesi enemmän.</span>.]]></message>
    <message id="err-VowIllN"><![CDATA[WORDFORM on illatiivissa, mutta <a class="helptext" target="_blank" href="/sme/gramm/substantiv.html#Illatiiva">vokaalivaihtelu<span class="shortinfo">Sanan viimeinen vokaali muuttuu illatiivipäätteen takia: a > i, i > á, o > u. Klikkaa lukeaksesi enemmän.</span> puuttuu.]]></message>
    <message id="err-VowCom"><![CDATA[<a class="helptext" target="_blank" href="/sme/gramm/substantiv.html#Komitatiiva">Vokaalin pitää muuttua<span class="shortinfo">Sanan viimeinen vokaali muuttuu komitatiivipäätteen takia: e > i. Klikkaa lukeaksesi enemmän.</span> komitatiivissa.]]></message>
    <message id="err-VowComN"><![CDATA[WORDFORM on komitatiivissa, mutta <a class="helptext" target="_blank" href="/sme/gramm/substantiv.html#Komitatiiva">vokaalivaihtelu<span class="shortinfo">Sanan viimeinen vokaali muuttuu komitatiivipäätteen takia: e > i. Klikkaa lukeaksesi enemmän.</span> puuttuu.]]></message>
    <message id="err-Diphsim"><![CDATA[WORDFORM : Sánis galgá <a class="helptext" target="_blank" href="#">diftoŋga njuolgat<span class="shortinfo">Diftoŋga nubbi vokála jávká: ea - e, ie - i, uo - u, oa - o.</span></a>.]]>.</message>
    <message id="err-Illsuf"><![CDATA[Kirjoitusvirhe, ehkä väärin kirjoitettu <a target="_blank" href="/sme/gramm/substantiv.html#Illatiiva">illatiivi?</a> Klikkaa lukeaksesi enemmän.]]></message>
    <message id="err-IllsufN"><![CDATA[WORDFORM lenee väärin kirjoitettu  <a target="_blank" href="/sme/gramm/substantiv.html#Illatiiva">illatiivi?</a> Klikkaa lukeaksesi enemmän.]]></message>
    <message id="grm-should-Ill"><![CDATA[WORDFORM pitää olla illatiivissa <a class="helptext" target="_blank" href="/sme/gramm/syntaks.html#Rekšuvnnat">verbin takia<span class="shortinfo">Tietŧt verbit, kuten liikot, vaativat illatiivia: guollái, guliide (vrt. suomen Pidän kalasta). Klikkaa lukeaksesi enemmän.</span></a>.]]></message>
    <message id="grm-should-not-Ess"><![CDATA[<a class="helptext" target="_blank" href="/sme/gramm/substantiv.html#Essiiva">Essiivi<span class="shortinfo">Saamen essiivi vastaa suomen essiiviä JA translatiivia. Kysymyssanat: manin, geanin. Klikkaa lukeaksesi enemmän essiivista.</span></a>.]]> ei sovi tähän.</message>
    <message id="grm-should-not-PP">Postpositio ei sovi tähän.</message>
    <message id="grm-incorr-nr-Pl">WORDFORM pitää olla monikossa jos on puhe monesta esineestä.</message>
    <message id="grm-incorr-nr-Sg">WORDFORM pitää olla yksikössä jos on puhe yhdestä esineestä.</message>
    <message id="grm-incorr-nr-Hab"><![CDATA[WORDFORM  pitää olla yksikön tai monikon kolmannessa persoonassa. Klikkaa jos haluat lukea <a target="_blank" href="/sme/gramm/syntaks.html#%27mus-lea%27-cealkagat+ja+eksistensiála+cealkagat">mus lea-lauseista</a>.]]></message>
	<message id="grm-incorr-persnr-v">Onko verbi WORDFORM taivutettu oikein?</message>
    <message id="grm-non-agr-subj-v"><![CDATA[Muista <a class="helptext" target="_blank" href="/sme/gramm/syntaks.html#Kongrueansa">kongruenssi subjektin ja verbin välillä<span class="shortinfo">Verbi taipuu subjektin persoonan ja luvun mukaan, kuten suomessakin esim. Mun boađán. Klikkaa lukeaksesi enemmän.</span></a>.]]></message>
    <message id="grm-incorr-tense">Oletko varma, että käytät oikeaa aikamuotoa?</message>
    <message id="grm-missing-ActEss"><![CDATA[Tähän sopii <a class="helptext" target="_blank" href="/sme/gramm/verb.html#Aktio+essiiva">aktio essiivi<span class="shortinfo">Aktio essiivi on esim. 'lea boahtime/boahtimin'. Klikkaa lukeaksesi enemmän.</span></a>.]]></message>
    <message id="grm-should-negV"><![CDATA[WORDFORM on väärässä muodossa, muista, että se tässä tulee kieltoverbin jälkeen ja pitää siis olla <a class="helptext" target="_blank" href="/sme/gramm/verb.html#Biehttaleapmi">kieltomuodossa<span class="shortinfo">Kieltomuodot ovat saamessa kuten suomessakin identtisiä yksikön imperatiivin kanssa (boađe, bora, goaro), ja preteritissä identtisiä partisiipin kanssa (boahtán, borran, gorron). Klikkaa lukeaksesi enemmän.</span></a>.]]></message>
    <message id="grm-missing-Inf"><![CDATA[WORDFORM pitää olla <a class="helptext" target="_blank" href="#">infinitiivimuodossa<span class="shortinfo">Infinitiivi on verbin perusmuoto, esim: borrat, lohkat</span></a>.]]></message>
    <message id="grm-should-not-ConNeg"><![CDATA[Ei sovi kirjoittaa kahta <a class="helptext" target="_blank" href="/sme/gramm/verb.html#Biehttaleapmi">kieltomuotoa<span class="shortinfo">Preesensissä kieltomuoto on esim. boađe, bora, goaro, ja preteritissä: boahtán, borran, gorron. Klikkaa lukeaksesi enemmän.</span></a>.]]></message>
    <message id="err-grm-Px-Loc"><![CDATA[Pitikö WORDFORM olla lokatiivissa? Muista <a class="helptext" target="_blank" href="/sme/gramm/stadieveksling.html">astevaihtelu<span class="shortinfo"> Saamen astevaihtelu on laajempi kuin suomen, se koskee miltei kaikkia konsonanttia, esim. giella - giela. Klikkaa lukeaksesi enemmän astevaihtelusta.</span></a>.]]>.</message>
    <message id="err-CG"><![CDATA[Muista <a class="helptext" target="_blank" href="/sme/gramm/stadieveksling.html">astevaihtelu<span class="shortinfo"> Saamen astevaihtelu on laajempi kuin suomen, se koskee miltei kaikkia konsonanttia, esim. giella - giela. Klikkaa lukeaksesi enemmän astevaihtelusta.</span></a>.]]></message>
    <message id="grm-missing-NumSg">Vastauksen pitää sisältää lukusana yksikössä.</message>
    <message id="grm-missing-NumPl"><![CDATA[Vastauksen pitää sisältää  <a class="helptext" target="_blank" href="/sme/gramm/logut.html#Eaŋkilis+lohkosánit+attribuhttan+substantiivii">lukusana monikossa<span class="shortinfo">esim. guovttit gápmagat = kahdet kengät. Klikkaa lukeaksesi enemmän.</span></a>.]]></message>
    <message id="grm-missing-NumLoc">Vastauksen pitää sisältää lukusana lokatiivissa.</message>
    <message id="grm-missing-NNum">Vastauksen pitää sisältää kollektiiviluku tai lukusana lokatiivissa.</message>
    <message id="grm-missing-Ord"><![CDATA[Vastauksesi pitää sisältää <a class="helptext" href="#">järjestysluku<span class="shortinfo">esim. nubbi, goalmmát, njealját.</span></a>.]]></message>
    <message id="grm-wrong-case">Oletko varma, että sanalla WORDFORM on oikea sijamuoto?</message>
    <message id="grm-missing-Acc"><![CDATA[Vastauksessa tulee käyttää <a class="helptext" target="_blank" href="/sme/gramm/substantiv.html#Akkusatiiva"> akkusatiivia <span class="shortinfo"> Objektin sija, huom., että akkusatiivi on saamessa genetiivin kaltainen myös monikossa, ei vaan yksikössä, kuten suomessa, esim. girjji, girjjiid. Kysymyssanat: maid, man, gean, geaid. Klikkaa lukeaksesi enemmän akkusatiivista. </span></a>.]]></message>
    <message id="grm-all-Acc"><![CDATA[Muista <a class="helptext" target="_blank" href="/sme/gramm/substantiv.html#Akkusatiiva"> akkusatiivia <span class="shortinfo"> Objektin sija, huom., että akkusatiivi on saamessa genetiivin kaltainen myös monikossa, ei vaan yksikössä, kuten suomessa, esim. girjji, girjjiid. Kysymyssanat: maid, man, gean, geaid. Klikkaa lukeaksesi enemmän akkusatiivista. </span></a>  joka sanassa, joka tarvitsee sitä.]]> </message>
    <message id="grm-missing-Gen"><![CDATA[Vastauksessa tulee käyttää <a class="helptext" target="_blank" href="/sme/gramm/substantiv.html#Genitiiva">genetiiviä<span class="shortinfo">Genetiivi vastaa suomen genetiivia, mutta myös usein partitiivia: nissona, nissoniid. Sitä käytetään sekä post- ja prepositioilmauksissa: nissona luhtte, birra jandora, ja lukusanojen jälkeen: golbma 'bártni'. Klikkaa lukeaksesi enemmän genetiivistä.</span></a>.]]></message>
    <message id="grm-missing-Com"><![CDATA[Vastauksessa tulee käyttää <a class="helptext" target="_blank" href="/sme/gramm/substantiv.html#Komitatiiva">komitatiivia<span class="shortinfo">Suom komitatiivin lisäksi saamen komitatiivi vastaa myös suomen "lla": niibbiin, "veitsellä". Klikkaa lukeaksesi enemmän komitatiivista.</span></a> verbin jälkeen.]]></message>
    <message id="grm-missing-Ill"><![CDATA[Vastauksessa tulee käyttää <a class="helptext" target="_blank" href="/sme/gramm/substantiv.html#Illatiiva">illatiivia<span class="shortinfo">Tietyt verbit, esim. liikot, vaativat illatiivia: guollái, guliide (ks. suomen pidän kalasta). Klikkaa lukeaksesi enemmän illatiivista.</span></a>.]]></message>
    <message id="grm-missing-Loc"><![CDATA[Vastauksessa tulee käyttää <a class="helptext" target="_blank" href="/sme/gramm/substantiv.html#Lokatiiva">lokatiivia<span class="shortinfo">Lokatiivi vastaa suomen inessiviä, allatiivia, elatiivia ja ablatiivia. Klikkaa lukeaksesi enemmän lokatiivista.</span></a>.]]></message>
    <message id="grm-Hab-Nom"><![CDATA[Se, mikä jollakulla on, pitää olla  <a class="helptext" target="_blank" href="/sme/gramm/syntaks.html#%27mus-lea%27-cealkagat+ja+eksistensiála+cealkagat">nominatiivissa<span class="shortinfo">, myös kieltolauseessa. Esim.: Mánás lea / ii leat spábba. Klikkaa lukeaksesi enemmän tästä.</span></a>.]]>.</message>
    <message id="grm-missing-Nom"><![CDATA[Vastauksessa tulee käyttää <a class="helptext" target="_blank" href="/sme/gramm/substantiv.html#Nominatiiva">nominatiivi<span class="shortinfo">Nominatiivi vastaa suomen nominatiivia, esim. gussa, gusat, mutta sitä ei käytetä monikko-objektin sijana. Kysymyssanat: mii, mat, gii, geat. Klikkaa lukeaksesi enemmän nominatiivista.</span></a>.]]></message>
    <message id="grm-missing-Ess"><![CDATA[Vastauksessa tulee käyttää <a class="helptext" target="_blank" href="/sme/gramm/substantiv.html#Essiiva">essiiviä.<span class="shortinfo">Essiivi vastaa suomen esiiviä ja translatiivia. Kysymyssanat ovat: manin, geanin. Klikkaa lukeaksesi enemmän essiivistä.</span></a>.]]></message>
    <message id="grm-Vehicle-Com"><![CDATA[Ajoneuvon pitää olla <a class="helptext" target="_blank" href="/sme/gramm/substantiv.html#Komitatiiva">komitatiivissa<span class="shortinfo">Suom komitatiivin lisäksi saamen komitatiivi vastaa myös suomen "lla": niibbiin, "veitsellä". Klikkaa lukeaksesi enemmän komitatiivista.</span></a> verbin jälkeen.]]></message>
    <message id="grm-Loc-leaving"><![CDATA[HUOM! <a class="helptext" target="_blank" href="/sme/gramm/substantiv.html#Lokatiiva">Lokatiivi<span class="shortinfo">Lokatiivi: skuvllas, skuvllain. Kysymyssanat ovat: mas, main, gos. Klikkaa jos haluat lukea enemmän.</span></a> kattaa sekä (suomen) illatiivin että elatiivin.]]></message>
    <message id="grm-missing-Loc-PP"><![CDATA[Vastauksessa tulee käyttää <a class="helptext" target="_blank" href="/sme/gramm/substantiv.html#Lokatiiva">lokatiivia<span class="shortinfo">Lokatiivi vastaa suomen inessiviä, allatiivia, elatiivia ja ablatiivia. Klikkaa lukeaksesi enemmän lokatiivista.</span></a>.]]></message>
    <message id="grm-missing-Ill-PP"><![CDATA[Vastauksessa tulee käyttää <a class="helptext" target="_blank" href="/sme/gramm/substantiv.html#Illatiiva">illatiivia<span class="shortinfo">Tietyt verbit, esim. liikot, vaativat illatiivia: guollái, guliide (ks. suomen pidän kalasta). Klikkaa lukeaksesi enemmän illatiivista.</span></a>.]]></message>
    <message id="grm-missing-Gen-PP"><![CDATA[Postposition edessä nomini on <a class="helptext" target="_blank" href="/sme/gramm/substantiv.html#Genitiiva">genetiivissä<span class="shortinfo">Genetiivi vastaa suomen genetiivia, mutta myös usein partitiivia: nissona, nissoniid. Sitä käytetään sekä post- ja prepositioilmauksissa: nissona luhtte, birra jandora, ja lukusanojen jälkeen: golbma 'bártni'. Klikkaa lukeaksesi enemmän genetiivistä.</span></a>.]]></message>
    <message id="grm-should-Ess"><![CDATA[WORDFORM pitää mielummin olla <a class="helptext" target="_blank" href="/sme/gramm/substantiv.html#Essiiva">essiivissä<span class="shortinfo">Mii geavaheimmet tealttá 'viessun'. 'Arvin' in gille oaggut. Kysymyssanat ovat: manin, geanin. Klikkaa lukeaksesi enemmän.</span></a>?]]></message>
    <message id="grm-should-Gen"><![CDATA[WORDFORM pitää mielummin olla <a class="helptext" target="_blank" href="/sme/gramm/substantiv.html#Genetiiva">genetiivissä<span class="shortinfo">Genetiivi ilmaisee omistussuhdetta: nissona biila = naisen auto. Genetiivi käytetään myös post- ja prepositiofraaseissa: nissona luhtte, ja lukusanojen jälkeen (paitsi 1): golbma 'bártni'. Klikkaa lukeaksesi enemmän.</span></a>?]]></message>
    <message id="grm-should-Nom"><![CDATA[WORDFORM pitää mielummin olla <a class="helptext" target="_blank" href="/sme/gramm/substantiv.html#Nominatiiva">nominatiivissa<span class="shortinfo"> Nominatiivi on sanan perussija, esim. gussa, gusat. Kysymyssanat ovat: mii, mat, gii, geat. Klikkaa lukeaksesi enemmän.</span></a>.]]></message>
    <message id="grm-should-Plur"><![CDATA[Objekti pitää olla <a class="helptext" href="#">monikossa<span class="shortinfo">Esimerkkiä akkusatiivin monikosta: girjjiid, mánáid</span></a>.]]></message>
    <message id="grm-should-LocPP"><![CDATA[Oletko varma, että <a target="_blank" href="/sme/gramm/pp.html">postpositio</a> sopii kysymykseen?]]></message>
    <message id="grm-should-IllPP"><![CDATA[Oletko varma, että <a target="_blank" href="/sme/gramm/pp.html">postpositio</a> sopii kysymykseen?]]></message>
    <message id="grm-should-not-Nom"><![CDATA[Objektin pitää olla <a class="helptext" target="_blank" href="/sme/gramm/substantiv.html#Akkusatiiva">akkusatiivissa<span class="shortinfo">esim. 'girjji' eikä 'girji'. Klikkaa lukeaksesi enemmän.</span></a>.]]></message>
	<message id="grm-should-Acc-time"><![CDATA[Aika pitää olla genetivissa tai akkusatiivissa, esim. 'geasi' eikä  'geassi'.]]></message>
    <message id="grm-should-pron">Tähän sopii käyttää pronominia ennen verbiä.</message>
    <message id="grm-NoEret">Muista "eret" paikannimen jälkeen.</message>
    <message id="grm-non-agreement-Dem"><![CDATA[Muista <a class="helptext" target="_blank" href="/sme/gramm/pronomen.html#Čujuheaddji+pronomenat+ovttas+substantiivvain">kongruenssi<span class="shortinfo">Pronomini taipuu substantiivin sijamuodon mukaan. Klikkaa lukeaksesi enemmän.</span></a> demonstratiivipronominin ja substantiivin välissä.]]></message>
    <message id="grm-non-agreement-Adj"><![CDATA[Muista <a class="helptext" target="_blank" href="/sme/gramm/adjektiver.html#Attribuhtta+ja+predikatiiva">kongruenssi<span class="shortinfo">Esim. jos substantiivi on monikossa, niin adjektiivinkin pitää olla monikossa. Klikkaa lukeaksesi enemmän.</span></a> subjektin ja adjektiivin välissä.]]></message>
    <message id="grm-non-agreement-Num"><![CDATA[Muista <a class="helptext" target="_blank" href="/sme/gramm/logut.html#Eaŋkilis+lohkosánit+attribuhttan+substantiivii">kongruenssi<span class="shortinfo">Kun luksana on yksikössä, niin substantiivinkin pitää olla yksikössä. Lukusanan sijamuodon pitää sopia substantiivin sijamuotoon. Klikkaa lukeaksesi enemmän.</span></a> lukusanan ja substantiivin välissä.]]></message>
    <message id="grm-non-agreement-buorre"><![CDATA[Muista kongruenssi <a class="helptext" target="_blank" href="/sme/gramm/adjektiver.html#%27buorre%27+attribuhttan">'buorre'-sanan<span class="shortinfo">'buorre' on erikoinen adjektiivi, joka taipuu myös attribuutinoa, esim. buorit biktasat. Klikkaa lukeaksesi enemmän.</span></a> ja substantiivin välissä.]]></message>
    <message id="grm-shouldAttr"><![CDATA[WORDFORM berrešii leat <a class="helptext" target="_blank" href="/sme/gramm/adjektiver.html#Attribuhtta+ja+predikatiiva">attribuhttahámis<span class="shortinfo">Adjektiivvas lea sierra hápmi go boahtá ovdal substantiivva, omd. 'rukses' dan sajis go 'ruoksat'. Klikkaa lukeaksesi enemmän.</span></a>.]]></message>
    <message id="grm-shouldNotAttr"><![CDATA[WORDFORM ei pitää olla <a class="helptext" target="_blank" href="/sme/gramm/adjektiver.html#Attribuhtta+ja+predikatiiva">attribuuttimuodossa<span class="shortinfo">Adjektiivissa on erillinen muoto, joka esiintyy ennen substantiivia, esim. 'rukses' eikä 'ruoksat'. Klikkaa lukeaksesi enemmän.</span> tässä</a>.]]></message>
    <message id="grm-incorr-time-expr">Ajan ilmaisu ei ehkä sovi tähän?</message>
    <message id="grm-incorr-tense-future">Ajan ilmaisu, joka viittaa ajassa eteenpäin ei ehkä sovi tähän?</message>
    <message id="grm-incorr-tense-past">Ajan ilmaisu ei pitäisi näyttää mennyttä aikaa?</message>
    <message id="grm-falAdv">"fal" ei voi esiintyä lauseen alussa.</message>
    <message id="grm-naPcle">"na" voi ainoastaan esiintyä lauseen alussa.</message>
    <message id="grm-notInterj"><![CDATA[WORDFORM on <a class="helptext" href="#">interjektio<span class="shortinfo">huutosana, esim. gea, a-a, hei</span></a> ja esiintyy ainoastaan lauseen alussa tai lopussa.]]></message>
    <message id="sem-not_wordlist">Käytä tässä sanoja vasemman reunan sanalistasta.</message>
    <message id="sem-not_correct_adj">Et käyttänyt oikeaa adjektiivia. Yritä uudestaan.</message>
    <message id="sem-not_correct_infl"><![CDATA[Adjektiivi ei ole <a target="_blank" href="/sme/gramm/adjektiver.html">taivutettu</a> oikein. Katso uudestaan.]]></message>
    <message id="grm-numeral-wrong-case"><![CDATA[Tarkista WORDFORM-sanan taivutus, se tulee <a class="helptext" target="_blank" href="/sme/gramm/logut.html#Eaŋkilis+lohkosánit+attribuhttan+substantiivii">lukusanan jälkeen<span class="shortinfo">Jos lukusana on yksikössä, niin substantiivin pitää myös olla yksikössä: golbma láibbi. Lukusanat taipuvat sijan mukaan. Klikkaa lukeaksesi enemmän.</span></a>.]]></message>
  </messages>
