<?xml version="1.0" encoding="UTF-8"?>
<!DOCTYPE document PUBLIC "-//APACHE//DTD Documentation V2.0//EN"
"http://forrest.apache.org/dtd/document-v20.dtd">
<document>
  <header>
    <title>Sojahallanhárjehusat</title>
  </header>

  <body>   
  
        <p>Dás galget leat guokte sojahallanfálaldaga. Killerfiller gullá VISLii ja don sojahat sániid cealkagiin. Sojahallanlanjas beasat hárjehallat sojahit eaŋkilsániid.</p>

      <p>Killerfilleris sáhtát válljet makkár sátneluohkáin háliidat bargat, ja sáhtát ieš válljet dási, maid váddáseabbo áššiid, nugo sojahit oamastangehčosiid.</p>
 
    <p>Oassi min resurssain leat beta-veršuvnnat mii máksá ahte sáhttet leat meattáhusat, ja maid ahte leat buoridanvejolašvuođat. Mii váldit áinnas vuostá kommentáraid! (oahpa@uit.no) </p>

    <ul>
      <li><a href="morphdrill.html">(Sojahallanlatnja)</a></li>
      <li><a href="Killerfiller_sme.html">Killerfiller čilgehusaiguin</a></li>
      <li><a href="http://beta.visl.sdu.dk/visl2/killerfiller.html">Killerfiller VISL njuolggoliŋka</a></li>	  
    </ul>
    
        <p>Dárbbašat go veahki grammatihkain? Mana dása: 
        <a href="../gramm/grammatihkka.html">Grammatihkka</a></p>
    
        <p>Sojahanparadigmaid sáhtát geahččat dás: 
        <a href="http://giellatekno.uit.no/cgi/p-sme.sme.html">Sojahanparadigmat</a></p>
   
<p class="last_modified" >Last changed: $Id: intro.xml,v 1.8 2008/02/15
	lene Exp $
                </p>
  </body>
</document>
