<?xml version="1.0" encoding="UTF-8"?>
<!-- default grammatical information for elements in question files -->

<tags>
  <element type="SUBJ">
    <grammar pos="Pron" tag="Pron+Pers+Person-Number+Nom"/>
    <grammar pos="N" tag="N+Number+Nom"/>
  </element>
  <element type="MAINV">
    <grammar pos="V" tag="V+Mood+Tense+Person-Number"/>
  </element>  
  <element type="N-ILL">
    <grammar pos="N" tag="N+Number+Ill"/>
  </element>
  <element type="N-LOC">
    <grammar pos="N" tag="N+Number+Loc"/>
  </element>
  <element type="N-COM">
    <grammar pos="N" tag="N+Number+Com"/>
  </element>
  <element type="N-ACC">
    <grammar pos="N" tag="N+Number+Acc"/>
  </element>
  <element type="N-GEN">
    <grammar pos="N" tag="N+Number+Gen"/>
  </element>
  <element type="OBJ">
    <grammar pos="N" tag="N+Number+Acc"/>
  </element>
</tags>
