<?xml version="1.0" encoding="UTF-8"?>
<!DOCTYPE document PUBLIC "-//APACHE//DTD Documentation V2.0//EN"
"http://forrest.apache.org/dtd/document-v20.dtd">
<document>
  <header>
    <title>Davvisámegiela veahkkereaiddut</title>
  </header>

  <body>
<!--  <p><a href="index.html">Sámegillii</a> | <em>På norsk</em> | <a href="index.eng.html">In English</a> | <a href="index.fin.html">Suomeksi</a> | <a href="index.swe.html">På svenska</a></p> -->
  
  <p></p>

    <p>Dás leat veahkkeneavvut daidda geat leat oahpahallame davvisámegiela, dahje geain leat mánát geat leat oahpahallame davvisámegiela.</p>
 <ul>
      <li><a href="http://oahpa.no/davvi/">OAHPA-davvi</a></li>
      <li><a href="http://kursa.oahpa.no/">Kursa - oahppanbálgát</a></li>
      <li><a href="gramm/grammatihkka.html">Grammatihkka</a></li>
      <li><a href="http://giellatekno.uit.no/cgi/p-sme.sme.html">Veahkki sojahit sániid</a></li>
      <li><a href="http://sanit.oahpa.no/">Neahttadigisánit</a></li>
      <li><a href="http://giellatekno.uit.no/num.sme.html">Logut, diibmomearit ja dáhtonat</a></li>
      <li><a href="http://giellatekno.uit.no/cgi/geo.sme.html">GEO - báikenamat</a></li>
      <li><a href="http://victorio.uit.no/cgi-bin/francis/index.php?lang=sme">Jorgalanveahkki</a></li>
      <li><a href="http://divvun.no/">Divvun-prográmma</a></li>
    </ul> 
<p></p>

  </body>
</document>
